{
  "schema_version": "0.1.0",
  "source": {
    "filename": "INR-18650-P30B.pdf",
    "model_name": "INR-18650-P30B",
    "file_hash": "9d5dd80c32f2dc7306396e9f3bf2a752fe8ce55a9a78c003a2abd461c9535c7a",
    "page_count": 2,
    "extracted_at": "2026-01-27T17:39:49.777338+00:00"
  },
  "cell": {
    "format": "cylindrical",
    "chemistry": "NMC",
    "model_name": "INR-18650-P30B",
    "size_code": "18650"
  },
  "specs": {
    "charge_voltage": {
      "value": 4.2,
      "unit": "V",
      "raw": {
        "text": "Cell Voltage Charge 4.2 V",
        "confidence": 0.6,
        "page": 1
      }
    },
    "weight": {
      "value": 47.0,
      "unit": "g",
      "raw": {
        "text": "Weight 47 g (Max)",
        "confidence": 0.6,
        "page": 1
      }
    },
    "diameter": {
      "value": 18.6,
      "unit": "mm",
      "raw": {
        "text": "Diameter 18.6 mm (Max)",
        "confidence": 0.6,
        "page": 1
      }
    },
    "height": {
      "value": 65.2,
      "unit": "mm",
      "raw": {
        "text": "Height 65.2 mm (Max)",
        "confidence": 0.6,
        "page": 1
      }
    },
    "max_charge_current": {
      "value": 9.0,
      "unit": "A",
      "raw": {
        "text": "Charge Current Maximum 9A",
        "confidence": 0.6,
        "page": 1
      }
    }
  }
}