{
  "schema_version": "0.1.0",
  "electrolyte_spec": {
    "id": "https://w3id.org/battinfo/electrolyte-spec/gzt2-hrqq-gsfn-sp94",
    "short_id": "gzt2hr",
    "name": "7M KOH in H2O",
    "family": "aqueous",
    "salt": {
      "name": "KOH",
      "material_spec_id": "https://w3id.org/battinfo/material-spec/s9h8-dfbw-zs4k-2qk8",
      "cation": "K+",
      "anion": "OH-",
      "property": {
        "concentration": {
          "value": 7.0,
          "unit": "mol/L"
        }
      }
    },
    "solvent_mixture": {
      "component": [
        {
          "name": "Water"
        }
      ]
    },
    "property": {
      "conductivity": {
        "value": 600.0,
        "unit": "mS/cm"
      }
    }
  },
  "provenance": {
    "source_type": "datasheet",
    "retrieved_at": 1781768181
  },
  "notes": [
    "Aqueous alkaline electrolyte, 7M KOH in water (e.g. Zn-MnO2 / Zn-air)."
  ]
}
